vertool/__init__.py
vertool/__main__.py
vertool/versioning.py
vertool-1.1.1.data/scripts/__main__.py
vertool-1.1.1.dist-info/LICENSE
vertool-1.1.1.dist-info/METADATA
vertool-1.1.1.dist-info/WHEEL
vertool-1.1.1.dist-info/entry_points.txt
vertool-1.1.1.dist-info/top_level.txt
vertool-1.1.1.dist-info/RECORD
