Metadata-Version: 2.1
Name: vertool
Version: 1.1.1
Summary: The project versioning controller
Home-page: https://bitbucket.org/celadonteam/vertool
Author: Celadon Developers
Author-email: opensource@celadon.ae
License: MIT
Platform: any
Classifier: Environment :: Console
Classifier: Environment :: Other Environment
Classifier: Intended Audience :: Developers
Classifier: Intended Audience :: Other Audience
Classifier: License :: OSI Approved :: MIT License
Classifier: Operating System :: OS Independent
Classifier: Programming Language :: Python :: 3.4
Classifier: Topic :: Software Development :: Debuggers
Classifier: Topic :: Software Development
Requires-Python: >=3.4
